nystrompca/__init__.py
nystrompca/algorithms/__init__.py
nystrompca/algorithms/bound.py
nystrompca/algorithms/kernel_PCA.py
nystrompca/algorithms/kernel_PCR.py
nystrompca/algorithms/kernel_RR.py
nystrompca/algorithms/nystrom_KPCA.py
nystrompca/algorithms/nystrom_KPCR.py
nystrompca/algorithms/nystrom_KRR.py
nystrompca/base/__init__.py
nystrompca/base/kernel.py
nystrompca/base/kernel_machine.py
nystrompca/base/nystrom_method.py
nystrompca/base/regression.py
nystrompca/base/transformation.py
nystrompca/data/airfoil.dat
nystrompca/data/cardiotocography.dat
nystrompca/data/dailykos.dat
nystrompca/data/drug.dat
nystrompca/data/magic_gamma_telescope.dat
nystrompca/data/nips.dat
nystrompca/data/segmentation.dat
nystrompca/data/yeast.dat
nystrompca/experiments/__init__.py
nystrompca/experiments/base_parser.py
nystrompca/experiments/bound_experiments.py
nystrompca/experiments/console_script.py
nystrompca/experiments/data.py
nystrompca/experiments/methods_experiments.py
nystrompca/experiments/plotting.py
nystrompca/experiments/regression_experiments.py
nystrompca/utils/__init__.py
nystrompca/utils/logger.py
nystrompca/utils/utils.py
nystrompca-1.0.2.data/data/data/airfoil.dat
nystrompca-1.0.2.data/data/data/cardiotocography.dat
nystrompca-1.0.2.data/data/data/dailykos.dat
nystrompca-1.0.2.data/data/data/drug.dat
nystrompca-1.0.2.data/data/data/magic_gamma_telescope.dat
nystrompca-1.0.2.data/data/data/nips.dat
nystrompca-1.0.2.data/data/data/segmentation.dat
nystrompca-1.0.2.data/data/data/yeast.dat
nystrompca-1.0.2.dist-info/LICENSE
nystrompca-1.0.2.dist-info/METADATA
nystrompca-1.0.2.dist-info/WHEEL
nystrompca-1.0.2.dist-info/entry_points.txt
nystrompca-1.0.2.dist-info/top_level.txt
nystrompca-1.0.2.dist-info/RECORD
